{
  "project_info": {
    "project_number": "776271210054",
    "project_id": "hatly-driver",
    "storage_bucket": "hatly-driver.appspot.com"
  },
  "client": [
    {
      "client_info": {
        "mobilesdk_app_id": "1:776271210054:android:ef7061b00572cdd73e8c47",
        "android_client_info": {
          "package_name": "com.teamx.hatly"
        }
      },
      "oauth_client": [],
      "api_key": [
        {
          "current_key": "AIzaSyAdbi6OchuK56J8ZHk1hyRPdxwOIcfvSCw"
        }
      ],
      "services": {
        "appinvite_service": {
          "other_platform_oauth_client": []
        }
      }
    }
  ],
  "configuration_version": "1"
}